[
    {
        "user_id": 1,
        "is_active": 1,
        "cv": "cv.docx",
        "money": "100000",
        "is_free": 1,
        "star": 4.5,
        "score": 5,
        "taught": "144",
        "phone": "01649199605",
        "description": "Chuyên môn giảng dạy nhưng môn tự nhiên, đã có kinh nghiệm giảng dạy ở nhiều năm..Môn dạy ưa thích là môn Toán",
        "grade": [1],
        "salary": 100023
    },
    {
        "user_id": 2,
        "is_active": 1,
        "cv": "cv.docx",
        "money": "200000",
        "is_free": 1,
        "star": 4,
        "score": 1050,
        "taught": "333",
        "phone": "01649194545",
        "description": "Yêu nghề, yêu thích học sinh. Đã có nhiều năm kinh nghiệm trong lĩnh vực giảng dạy. Có thâm niên giảng dạy trong trường THPT chuyên hà nội",
        "grade": [2],
        "salary": 200000
    },
    {
        "user_id": 3,
        "is_active": 1,
        "cv": "cv.docx",
        "money": "200000",
        "is_free": 1,
        "star": 5,
        "score": 9,
        "taught": "333",
        "phone": "0484759578",
        "description": "Là giáo viên dạy giỏi nhiều năm, có thành tích tốt trong giảng dạy..",
        "grade": [3],
        "salary": 200000
    },
    {
        "user_id": 4,
        "is_active": 0,
        "cv": "cv.docx",
        "money": "200",
        "is_free": 0,
        "star": 1,
        "score": 10,
        "taught": "4.jpg",
        "phone": "0164919123",
        "description": "Yêu nghề và mong muốn đào tạo ra những nhân tài cho đất nước",
        "grade": [1,2,3],
        "salary": 200000
    },
    {
        "user_id": 5,
        "is_active": 0,
        "cv": "cv.docx",
        "money": "100",
        "is_free": 1,
        "star": 2,
        "score": 5,
        "taught": "333",
        "phone": "01649145265",
        "description": "Là giáo viên kì cựu của trường THPT Hà Nội",
        "grade": [1,2],
        "salary": 200000
    },
    {
        "user_id": 6,
        "is_active": 1,
        "cv": "lalal.doc",
        "money": "20000",
        "is_free": 1,
        "star": 4,
        "score": 3,
        "taught": "1.jpg",
        "phone": "01649199566",
        "description": "Tôi là giáo viên dạy giỏi, hãy cùng tôi phát triển và xây dựng đất nước",
        "grade": [1,2],
        "salary": 200000
    },
    {
        "user_id": 7,
        "is_active": 1,
        "cv": "cai_gi_the_nay.doc",
        "money": "1562",
        "is_free": 1,
        "star": 4.5,
        "score": 10,
        "taught": "33",
        "phone": "01649199222",
        "description": "Hãy dõi theo Thầy để được hấp thụ những tinh hoa của kiến thức",
        "grade": [1,2],
        "salary": 200000
    },
    {
        "user_id": 8,
        "is_active": 1,
        "cv": "sd.doc",
        "money": "2562",
        "is_free": 1,
        "star": 3,
        "score": 8,
        "taught": "33",
        "phone": "01649199562",
        "description": "Không nói nhiều, qua đây và cảm nhận nào",
        "grade": [1,2,3],
        "salary": 200000
    },
    {
        "user_id": 9,
        "is_active": 1,
        "cv": "dd.doc",
        "money": "145",
        "is_free": 1,
        "star": 4.5,
        "score": 1000,
        "taught": "333",
        "phone": "01649199605",
        "description": "Chuyên văn",
        "grade": [1,2],
        "salary": 200000
    },
    {
        "user_id": 10,
        "is_active": 1,
        "cv": "526.doc",
        "money": "4562",
        "is_free": 1,
        "star": 4.5,
        "score": 1000,
        "taught": "333",
        "phone": "01649199605",
        "description": "Chuyên toán",
        "grade": [1,2],
        "salary": 200000
    }
]
